{"type":"FeatureCollection","features":[{"type":"Feature","properties":{},"geometry":{"type":"Polygon","coordinates":[[[143.41549,-35.3656],[143.41555,-35.3656],[143.41554,-35.36567],[143.41548,-35.36567]]]}},{"type":"Feature","properties":{"h":0.7},"geometry":{"type":"Polygon","coordinates":[[[143.41631,-35.36525],[143.41643,-35.36525],[143.41643,-35.36534],[143.41651,-35.36534],[143.4165,-35.36554],[143.4163,-35.36554]]]}},{"type":"Feature","properties":{"h":0.1},"geometry":{"type":"Polygon","coordinates":[[[143.41611,-35.36543],[143.41611,-35.36555],[143.41603,-35.36555],[143.41603,-35.36543]]]}},{"type":"Feature","properties":{"h":0.9},"geometry":{"type":"Polygon","coordinates":[[[143.41706,-35.3657],[143.4169,-35.36571],[143.41689,-35.36557],[143.41705,-35.36557]]]}},{"type":"Feature","properties":{"h":0.1},"geometry":{"type":"Polygon","coordinates":[[[143.41737,-35.36651],[143.41753,-35.36651],[143.41753,-35.36658],[143.41737,-35.36658]]]}},{"type":"Feature","properties":{"h":1.5},"geometry":{"type":"Polygon","coordinates":[[[143.44161,-35.37875],[143.44169,-35.37876],[143.44168,-35.37879],[143.4416,-35.37878]]]}},{"type":"Feature","properties":{"h":1.2},"geometry":{"type":"Polygon","coordinates":[[[143.44091,-35.37928],[143.44091,-35.37925],[143.44105,-35.37924],[143.44105,-35.37927]]]}},{"type":"Feature","properties":{"h":3.4},"geometry":{"type":"Polygon","coordinates":[[[143.44155,-35.37935],[143.44163,-35.37935],[143.44163,-35.37938],[143.44155,-35.37938]]]}}]}