{"type":"FeatureCollection","features":[{"type":"Feature","properties":{},"geometry":{"type":"Polygon","coordinates":[[[144.01561,-37.98656],[144.01561,-37.98661],[144.0154,-37.98661],[144.0154,-37.98642],[144.01558,-37.98642],[144.01558,-37.98656]]]}},{"type":"Feature","properties":{},"geometry":{"type":"Polygon","coordinates":[[[144.00234,-37.97473],[144.00244,-37.97474],[144.00243,-37.9748],[144.00233,-37.9748]]]}},{"type":"Feature","properties":{},"geometry":{"type":"Polygon","coordinates":[[[144.00242,-37.97498],[144.00252,-37.97499],[144.0025,-37.97506],[144.00241,-37.97505]]]}},{"type":"Feature","properties":{},"geometry":{"type":"Polygon","coordinates":[[[144.00183,-37.97523],[144.00183,-37.97516],[144.00194,-37.97516],[144.00193,-37.97523]]]}},{"type":"Feature","properties":{},"geometry":{"type":"Polygon","coordinates":[[[144.00202,-37.97451],[144.00212,-37.97452],[144.00211,-37.97459],[144.00201,-37.97458]]]}},{"type":"Feature","properties":{},"geometry":{"type":"Polygon","coordinates":[[[144.00234,-37.97452],[144.00244,-37.97454],[144.00242,-37.9746],[144.00232,-37.97459]]]}},{"type":"Feature","properties":{},"geometry":{"type":"Polygon","coordinates":[[[144.00763,-37.97397],[144.00763,-37.97404],[144.00753,-37.97404],[144.00753,-37.97397]]]}},{"type":"Feature","properties":{},"geometry":{"type":"Polygon","coordinates":[[[144.00791,-37.97395],[144.00791,-37.97402],[144.00781,-37.97402],[144.0078,-37.97395]]]}},{"type":"Feature","properties":{},"geometry":{"type":"Polygon","coordinates":[[[144.00819,-37.97383],[144.00809,-37.97386],[144.00806,-37.9738],[144.00816,-37.97377]]]}},{"type":"Feature","properties":{},"geometry":{"type":"Polygon","coordinates":[[[144.00876,-37.97296],[144.00887,-37.97296],[144.00886,-37.97303],[144.00876,-37.97302]]]}},{"type":"Feature","properties":{"h":4.0},"geometry":{"type":"Polygon","coordinates":[[[144.00839,-37.97319],[144.00849,-37.97321],[144.00847,-37.97328],[144.00836,-37.97326]]]}},{"type":"Feature","properties":{},"geometry":{"type":"Polygon","coordinates":[[[144.00826,-37.97352],[144.00827,-37.97345],[144.00838,-37.97347],[144.00836,-37.97354]]]}},{"type":"Feature","properties":{"h":5.0},"geometry":{"type":"Polygon","coordinates":[[[144.00767,-37.97314],[144.00773,-37.97308],[144.00779,-37.97312],[144.00773,-37.97318]]]}},{"type":"Feature","properties":{},"geometry":{"type":"Polygon","coordinates":[[[144.00677,-37.97293],[144.00687,-37.97294],[144.00686,-37.97301],[144.00676,-37.97299]]]}},{"type":"Feature","properties":{},"geometry":{"type":"Polygon","coordinates":[[[144.00636,-37.97319],[144.00637,-37.97312],[144.00647,-37.97313],[144.00646,-37.9732]]]}},{"type":"Feature","properties":{},"geometry":{"type":"Polygon","coordinates":[[[144.00713,-37.97406],[144.00716,-37.974],[144.00726,-37.97402],[144.00723,-37.97409]]]}},{"type":"Feature","properties":{},"geometry":{"type":"Polygon","coordinates":[[[144.00679,-37.97403],[144.00688,-37.97406],[144.00685,-37.97413],[144.00675,-37.97409]]]}},{"type":"Feature","properties":{},"geometry":{"type":"Polygon","coordinates":[[[144.00612,-37.9734],[144.00606,-37.97342],[144.00603,-37.97337],[144.00609,-37.97335]]]}},{"type":"Feature","properties":{},"geometry":{"type":"Polygon","coordinates":[[[144.00642,-37.97341],[144.00642,-37.97348],[144.00631,-37.97347],[144.00631,-37.97341]]]}},{"type":"Feature","properties":{},"geometry":{"type":"Polygon","coordinates":[[[144.00732,-37.97232],[144.00737,-37.97226],[144.00745,-37.97231],[144.0074,-37.97237]]]}},{"type":"Feature","properties":{},"geometry":{"type":"Polygon","coordinates":[[[144.00767,-37.97192],[144.00775,-37.97196],[144.00771,-37.97202],[144.00762,-37.97198]]]}},{"type":"Feature","properties":{},"geometry":{"type":"Polygon","coordinates":[[[144.00809,-37.972],[144.00804,-37.97205],[144.00796,-37.97201],[144.00801,-37.97195]]]}},{"type":"Feature","properties":{"h":4.0},"geometry":{"type":"Polygon","coordinates":[[[144.00833,-37.9724],[144.00831,-37.97246],[144.00821,-37.97244],[144.00824,-37.97237]]]}},{"type":"Feature","properties":{"h":4.3},"geometry":{"type":"Polygon","coordinates":[[[144.00875,-37.97253],[144.0087,-37.97258],[144.00861,-37.97254],[144.00866,-37.97248]]]}},{"type":"Feature","properties":{},"geometry":{"type":"Polygon","coordinates":[[[144.01136,-37.95795],[144.01138,-37.95795],[144.01137,-37.958],[144.01135,-37.95799]]]}},{"type":"Feature","properties":{},"geometry":{"type":"Polygon","coordinates":[[[144.01131,-37.95784],[144.01132,-37.95781],[144.01139,-37.95782],[144.01138,-37.95785]]]}},{"type":"Feature","properties":{},"geometry":{"type":"Polygon","coordinates":[[[144.01793,-37.95875],[144.01799,-37.95875],[144.018,-37.95882],[144.01795,-37.95882]]]}},{"type":"Feature","properties":{},"geometry":{"type":"Polygon","coordinates":[[[144.01217,-37.98203],[144.01223,-37.98209],[144.01218,-37.98212],[144.01212,-37.98206]]]}}]}