{"type":"FeatureCollection","features":[{"type":"Feature","properties":{},"geometry":{"type":"Polygon","coordinates":[[[144.07953,-36.90411],[144.07961,-36.90415],[144.07957,-36.9042],[144.0795,-36.90417]]]}},{"type":"Feature","properties":{},"geometry":{"type":"Polygon","coordinates":[[[144.08984,-36.90037],[144.08984,-36.90031],[144.08989,-36.90031],[144.08989,-36.90037]]]}},{"type":"Feature","properties":{},"geometry":{"type":"Polygon","coordinates":[[[144.09249,-36.92494],[144.0925,-36.925],[144.09243,-36.92501],[144.09242,-36.92495]]]}},{"type":"Feature","properties":{},"geometry":{"type":"Polygon","coordinates":[[[144.09474,-36.93389],[144.09481,-36.93389],[144.09481,-36.93394],[144.09474,-36.93394]]]}},{"type":"Feature","properties":{"h":4.5},"geometry":{"type":"Polygon","coordinates":[[[144.06112,-36.93906],[144.06113,-36.939],[144.06121,-36.93902],[144.06119,-36.93907]]]}},{"type":"Feature","properties":{"h":4.1},"geometry":{"type":"Polygon","coordinates":[[[144.0588,-36.9469],[144.05881,-36.94685],[144.05889,-36.94686],[144.05888,-36.94691]]]}},{"type":"Feature","properties":{},"geometry":{"type":"Polygon","coordinates":[[[144.06505,-36.94641],[144.06504,-36.94644],[144.06499,-36.94644],[144.06499,-36.9464]]]}},{"type":"Feature","properties":{"h":4.7},"geometry":{"type":"Polygon","coordinates":[[[144.07176,-36.93386],[144.07182,-36.93385],[144.07184,-36.93388],[144.07178,-36.9339]]]}},{"type":"Feature","properties":{},"geometry":{"type":"Polygon","coordinates":[[[144.06426,-36.94835],[144.06434,-36.94833],[144.06438,-36.94844],[144.0643,-36.94846]]]}},{"type":"Feature","properties":{},"geometry":{"type":"Polygon","coordinates":[[[144.05679,-36.9496],[144.05683,-36.94965],[144.05679,-36.94967],[144.05674,-36.94963]]]}},{"type":"Feature","properties":{},"geometry":{"type":"Polygon","coordinates":[[[144.05136,-36.94845],[144.05137,-36.9485],[144.05124,-36.94852],[144.05122,-36.94847]]]}}]}