{"type":"FeatureCollection","features":[{"type":"Feature","properties":{"h":3.0},"geometry":{"type":"Polygon","coordinates":[[[145.9183,-36.34301],[145.9183,-36.34295],[145.91841,-36.34295],[145.91841,-36.343]]]}},{"type":"Feature","properties":{"h":4.0},"geometry":{"type":"Polygon","coordinates":[[[145.918,-36.34237],[145.918,-36.34235],[145.91812,-36.34233],[145.91813,-36.34235]]]}},{"type":"Feature","properties":{"h":7.1},"geometry":{"type":"Polygon","coordinates":[[[145.91202,-36.34608],[145.91184,-36.34607],[145.91184,-36.34586],[145.91202,-36.34587]]]}},{"type":"Feature","properties":{"h":3.6},"geometry":{"type":"Polygon","coordinates":[[[145.91168,-36.34564],[145.91182,-36.34563],[145.91183,-36.3457],[145.91168,-36.3457]]]}},{"type":"Feature","properties":{"h":4.1},"geometry":{"type":"Polygon","coordinates":[[[145.90019,-36.33048],[145.90019,-36.33056],[145.9001,-36.33056],[145.90009,-36.33049]]]}},{"type":"Feature","properties":{"h":4.0},"geometry":{"type":"Polygon","coordinates":[[[145.9002,-36.33045],[145.9002,-36.3304],[145.90026,-36.33041],[145.90026,-36.33045]]]}},{"type":"Feature","properties":{"h":3.6},"geometry":{"type":"Polygon","coordinates":[[[145.90721,-36.33066],[145.90721,-36.33052],[145.90726,-36.33053],[145.90726,-36.33067]]]}},{"type":"Feature","properties":{"h":3.3},"geometry":{"type":"Polygon","coordinates":[[[145.90694,-36.33194],[145.9068,-36.33194],[145.9068,-36.33186],[145.90694,-36.33187]]]}},{"type":"Feature","properties":{"h":4.0},"geometry":{"type":"Polygon","coordinates":[[[145.90737,-36.33139],[145.90748,-36.33139],[145.90748,-36.33148],[145.90737,-36.33147]]]}},{"type":"Feature","properties":{"h":3.6},"geometry":{"type":"Polygon","coordinates":[[[145.90612,-36.33153],[145.90612,-36.33143],[145.90618,-36.33143],[145.90618,-36.33153]]]}},{"type":"Feature","properties":{"h":3.6},"geometry":{"type":"Polygon","coordinates":[[[145.90638,-36.33157],[145.90638,-36.33161],[145.90621,-36.3316],[145.90621,-36.33156]]]}},{"type":"Feature","properties":{"h":3.0},"geometry":{"type":"Polygon","coordinates":[[[145.91724,-36.32046],[145.91725,-36.32054],[145.91717,-36.32054],[145.91717,-36.32047]]]}},{"type":"Feature","properties":{"h":0.1},"geometry":{"type":"Polygon","coordinates":[[[145.91807,-36.31954],[145.918,-36.31958],[145.91798,-36.31955],[145.91805,-36.31951]]]}},{"type":"Feature","properties":{"h":2.9},"geometry":{"type":"Polygon","coordinates":[[[145.92783,-36.3125],[145.92787,-36.3125],[145.92787,-36.31245],[145.92796,-36.31245],[145.92796,-36.31257],[145.92783,-36.31256]]]}},{"type":"Feature","properties":{"h":2.0},"geometry":{"type":"Polygon","coordinates":[[[145.928,-36.31221],[145.92806,-36.31221],[145.92807,-36.31233],[145.92801,-36.31233]]]}},{"type":"Feature","properties":{"h":3.6},"geometry":{"type":"Polygon","coordinates":[[[145.92829,-36.31238],[145.9283,-36.31245],[145.92818,-36.31245],[145.92818,-36.31238]]]}},{"type":"Feature","properties":{"h":2.9},"geometry":{"type":"Polygon","coordinates":[[[145.92886,-36.31253],[145.92886,-36.31262],[145.92872,-36.31262],[145.92871,-36.31253]]]}},{"type":"Feature","properties":{"h":2.9},"geometry":{"type":"Polygon","coordinates":[[[145.92913,-36.31235],[145.92913,-36.31245],[145.92907,-36.31245],[145.92907,-36.31236]]]}},{"type":"Feature","properties":{"h":4.0},"geometry":{"type":"Polygon","coordinates":[[[145.9284,-36.31198],[145.92834,-36.31198],[145.92834,-36.31194],[145.92841,-36.31194]]]}},{"type":"Feature","properties":{"h":2.9},"geometry":{"type":"Polygon","coordinates":[[[145.92796,-36.31199],[145.92797,-36.31208],[145.92783,-36.31208],[145.92782,-36.31199]]]}},{"type":"Feature","properties":{"h":3.2},"geometry":{"type":"Polygon","coordinates":[[[145.92744,-36.31211],[145.92743,-36.31194],[145.92754,-36.31194],[145.92755,-36.31211]]]}},{"type":"Feature","properties":{"h":3.0},"geometry":{"type":"Polygon","coordinates":[[[145.9109,-36.32076],[145.9109,-36.32079],[145.91082,-36.32079],[145.91082,-36.32076]]]}},{"type":"Feature","properties":{"h":2.0},"geometry":{"type":"Polygon","coordinates":[[[145.91082,-36.32116],[145.91082,-36.3211],[145.91088,-36.3211],[145.91089,-36.32115]]]}},{"type":"Feature","properties":{"h":3.4},"geometry":{"type":"Polygon","coordinates":[[[145.90763,-36.32234],[145.9077,-36.32234],[145.9077,-36.32252],[145.90762,-36.32252]]]}},{"type":"Feature","properties":{"h":3.8},"geometry":{"type":"Polygon","coordinates":[[[145.90745,-36.32249],[145.90745,-36.32253],[145.9074,-36.32253],[145.90741,-36.32248]]]}},{"type":"Feature","properties":{"h":3.0},"geometry":{"type":"Polygon","coordinates":[[[145.90832,-36.3202],[145.90832,-36.32023],[145.90825,-36.32024],[145.90825,-36.3202]]]}},{"type":"Feature","properties":{"h":4.0},"geometry":{"type":"Polygon","coordinates":[[[145.90038,-36.32086],[145.90037,-36.32086],[145.90038,-36.32082],[145.90036,-36.32082],[145.90037,-36.32076],[145.90048,-36.32078],[145.90045,-36.3209],[145.90037,-36.32089]]]}},{"type":"Feature","properties":{"h":2.8},"geometry":{"type":"Polygon","coordinates":[[[145.90027,-36.32056],[145.9004,-36.32056],[145.9004,-36.32069],[145.90026,-36.32069]]]}},{"type":"Feature","properties":{"h":3.0},"geometry":{"type":"Polygon","coordinates":[[[145.90054,-36.32085],[145.90057,-36.32084],[145.90059,-36.32087],[145.90055,-36.32088]]]}},{"type":"Feature","properties":{"h":3.9},"geometry":{"type":"Polygon","coordinates":[[[145.90104,-36.3012],[145.90104,-36.30124],[145.90092,-36.30124],[145.90092,-36.3012]]]}},{"type":"Feature","properties":{"h":3.0},"geometry":{"type":"Polygon","coordinates":[[[145.9008,-36.30122],[145.9008,-36.30138],[145.90072,-36.30137],[145.90072,-36.30122]]]}},{"type":"Feature","properties":{"h":3.6},"geometry":{"type":"Polygon","coordinates":[[[145.90039,-36.30099],[145.90039,-36.30093],[145.90046,-36.30093],[145.90047,-36.30099]]]}},{"type":"Feature","properties":{"h":3.2},"geometry":{"type":"Polygon","coordinates":[[[145.90053,-36.3007],[145.90053,-36.30082],[145.90039,-36.30082],[145.90039,-36.3007]]]}},{"type":"Feature","properties":{"h":1.6},"geometry":{"type":"Polygon","coordinates":[[[145.92936,-36.30523],[145.9294,-36.30524],[145.9294,-36.30531],[145.92936,-36.30531]]]}},{"type":"Feature","properties":{"h":1.0},"geometry":{"type":"Polygon","coordinates":[[[145.94658,-36.31821],[145.94664,-36.31823],[145.94661,-36.31829],[145.94655,-36.31827]]]}},{"type":"Feature","properties":{"h":1.0},"geometry":{"type":"Polygon","coordinates":[[[145.94632,-36.3179],[145.94629,-36.3179],[145.94628,-36.31778],[145.94632,-36.31778]]]}}]}